setup.py
bookScraper/__init__.py
bookScraper.egg-info/PKG-INFO
bookScraper.egg-info/SOURCES.txt
bookScraper.egg-info/dependency_links.txt
bookScraper.egg-info/not-zip-safe
bookScraper.egg-info/requires.txt
bookScraper.egg-info/top_level.txt