Metadata-Version: 1.0
Name: bookScraper
Version: 1.7
Summary: The funniest joke in the world
Home-page: UNKNOWN
Author: UNKNOWN
Author-email: UNKNOWN
License: UNKNOWN
Platform: UNKNOWN
